oss_policy_sign/__init__.py
oss_policy_sign/exceptions.py
oss_policy_sign/generator.py
oss_policy_sign/urls.py
oss_policy_sign/views.py
oss_policy_sign/tests/__init__.py
oss_policy_sign/tests/test_generator.py
oss_policy_sign-1.2.dist-info/LICENSE
oss_policy_sign-1.2.dist-info/METADATA
oss_policy_sign-1.2.dist-info/WHEEL
oss_policy_sign-1.2.dist-info/top_level.txt
oss_policy_sign-1.2.dist-info/RECORD
