Metadata-Version: 2.1
Name: oss-policy-sign
Version: 1.2
Summary: A django rest framework (DRF) policy sign for aliyun oss
Home-page: https://github.com/wyh/oss-policy-sign
Author: wyh
Author-email: samuel.yh.wu@gmail.com
License: UNKNOWN
Platform: UNKNOWN
Classifier: Programming Language :: Python :: 3
Classifier: License :: OSI Approved :: Apache Software License
Classifier: Operating System :: OS Independent
